rewalt/__init__.py
rewalt/diagrams.py
rewalt/drawing.py
rewalt/hasse.py
rewalt/ogposets.py
rewalt/shapes.py
rewalt/strdiags.py
rewalt/utils.py
tests/__init__.py
tests/test_diagrams.py
tests/test_ogposets.py
tests/test_shapes.py
rewalt-0.1.0.dist-info/LICENSE
rewalt-0.1.0.dist-info/METADATA
rewalt-0.1.0.dist-info/WHEEL
rewalt-0.1.0.dist-info/top_level.txt
rewalt-0.1.0.dist-info/RECORD
