Metadata-Version: 2.1
Name: rewalt
Version: 0.1.0
Summary: A toolkit for higher-dimensional diagram rewriting.
Home-page: https://rewalt.readthedocs.io
Download-URL: https://pypi.org/project/rewalt
Author: Amar Hadzihasanovic
Author-email: ahadziha@users.noreply.github.com
Project-URL: Source Code, https://github.com/ahadziha/rewalt
Keywords: category theory,higher category theory,rewriting,string diagrams,higher-dimensional rewriting,homotopy theory,combinatorial topology,cell complexes,diagram rewriting,diagrammatic rewriting,monoidal category,prop,operad,multicategory,simplicial set,cubical set
Classifier: Development Status :: 3 - Alpha
Classifier: Environment :: Console
Classifier: Intended Audience :: Science/Research
Classifier: License :: OSI Approved :: BSD License
Classifier: Operating System :: OS Independent
Classifier: Programming Language :: Python :: 3
Classifier: Programming Language :: Python :: 3.10
Classifier: Programming Language :: Python :: 3.9
Classifier: Programming Language :: Python :: 3.8
Classifier: Programming Language :: Python :: 3.7
Classifier: Natural Language :: English
Classifier: Topic :: Scientific/Engineering
Requires-Python: >=3.7
License-File: LICENSE
Requires-Dist: numpy (>=1.18.1)
Requires-Dist: networkx (>=2.4)
Requires-Dist: matplotlib (>=3.1.2)
Requires-Dist: pillow (>=6.2.1)
Provides-Extra: test
Requires-Dist: pytest ; extra == 'test'
